silverpeak/__init__.py
silverpeak/exceptions.py
silverpeak/silverpeak.py
silverpeak-0.0.3.9.dist-info/DESCRIPTION.rst
silverpeak-0.0.3.9.dist-info/METADATA
silverpeak-0.0.3.9.dist-info/RECORD
silverpeak-0.0.3.9.dist-info/WHEEL
silverpeak-0.0.3.9.dist-info/metadata.json
silverpeak-0.0.3.9.dist-info/top_level.txt
