Metadata-Version: 2.0
Name: silverpeak
Version: 0.0.3.9
Summary: A package to allow you to interact with the Silver Peak Orchestrator API
Home-page: https://github.com/minitriga/silverpeak_python
Author: Alex Gittings, Adam Jarvis
Author-email: alexgit@hotmail.co.uk, adamjohnjarvis1@gmail.com
License: UNKNOWN
Platform: UNKNOWN
Classifier: Programming Language :: Python :: 3
Classifier: License :: OSI Approved :: MIT License
Classifier: Operating System :: OS Independent
